asgi_webdav/__init__.py
asgi_webdav/__main__.py
asgi_webdav/auth.py
asgi_webdav/cache.py
asgi_webdav/cli.py
asgi_webdav/config.py
asgi_webdav/constants.py
asgi_webdav/core.py
asgi_webdav/exceptions.py
asgi_webdav/helpers.py
asgi_webdav/lock.py
asgi_webdav/log.py
asgi_webdav/property.py
asgi_webdav/request.py
asgi_webdav/response.py
asgi_webdav/server.py
asgi_webdav/web_dav.py
asgi_webdav/web_page.py
asgi_webdav/dev/__init__.py
asgi_webdav/dev/dev.py
asgi_webdav/dev/litmus.py
asgi_webdav/middleware/__init__.py
asgi_webdav/middleware/cors.py
asgi_webdav/middleware/debug.py
asgi_webdav/provider/__init__.py
asgi_webdav/provider/common.py
asgi_webdav/provider/file_system.py
asgi_webdav/provider/memory.py
asgi_webdav/provider/webhdfs.py
asgiwebdav-2.0.0.dist-info/licenses/LICENSE
asgiwebdav-2.0.0.dist-info/METADATA
asgiwebdav-2.0.0.dist-info/WHEEL
asgiwebdav-2.0.0.dist-info/entry_points.txt
asgiwebdav-2.0.0.dist-info/top_level.txt
asgiwebdav-2.0.0.dist-info/RECORD
